unitscvt/__init__.py
unitscvt/aunits.py
unitscvt/siconst.py
unitscvt-0.0.22.dist-info/LICENSE
unitscvt-0.0.22.dist-info/METADATA
unitscvt-0.0.22.dist-info/WHEEL
unitscvt-0.0.22.dist-info/top_level.txt
unitscvt-0.0.22.dist-info/RECORD
