Metadata-Version: 2.1
Name: unitscvt
Version: 0.0.22
Summary: Units conversion
Home-page: https://gitlab.fysik.su.se/lucas.borges/unitsconversion
Author: Lucas Borges
Author-email: Lucas Borges <lucas.borges@fysik.su.se>
License: MIT
Keywords: units
Classifier: Programming Language :: Python :: 3
Classifier: License :: OSI Approved :: MIT License
Classifier: Operating System :: OS Independent
Requires-Python: >=3.6
License-File: LICENSE
